AkhilShimnaKumar/DataAnalysis.py
AkhilShimnaKumar/Mowie.py
AkhilShimnaKumar/Vigenere.py
AkhilShimnaKumar/__init__.py
AkhilShimnaKumar/TnOComputeEngine/Node_Studio_Visual.py
AkhilShimnaKumar/TnOComputeEngine/TnOComputeEngine.py
AkhilShimnaKumar/TnOComputeEngine/__init__.py
AkhilShimnaKumar/automl/__init__.py
AkhilShimnaKumar/automl/automl.py
AkhilShimnaKumar/automl/evaluate.py
AkhilShimnaKumar/automl/model.py
AkhilShimnaKumar/automl/preprocess.py
AkhilShimnaKumar/automl/tune.py
AkhilShimnaKumar/automl/utils.py
akhilshimnakumar-3.8.11.dist-info/licenses/License.md
akhilshimnakumar-3.8.11.dist-info/METADATA
akhilshimnakumar-3.8.11.dist-info/WHEEL
akhilshimnakumar-3.8.11.dist-info/top_level.txt
akhilshimnakumar-3.8.11.dist-info/RECORD
