Metadata-Version: 2.4
Name: AkhilShimnaKumar
Version: 3.8.11
Summary: A package containing functions/shorthands that I would like to use in my Python programs.
Author: Akhil Shimna Kumar
License: Proprietary
Classifier: Programming Language :: Python :: 3
Classifier: License :: Other/Proprietary License
Classifier: Operating System :: OS Independent
Requires-Python: >=3.7
License-File: License.md
Dynamic: license-file
